LICENSE
MANIFEST.in
README.md
setup.py
tap_recharge/__init__.py
tap_recharge/client.py
tap_recharge/discover.py
tap_recharge/schema.py
tap_recharge/streams.py
tap_recharge/sync.py
tap_recharge.egg-info/PKG-INFO
tap_recharge.egg-info/SOURCES.txt
tap_recharge.egg-info/dependency_links.txt
tap_recharge.egg-info/entry_points.txt
tap_recharge.egg-info/requires.txt
tap_recharge.egg-info/top_level.txt
tap_recharge/schemas/addresses.json
tap_recharge/schemas/charges.json
tap_recharge/schemas/collections.json
tap_recharge/schemas/customers.json
tap_recharge/schemas/discounts.json
tap_recharge/schemas/metafields_customer.json
tap_recharge/schemas/metafields_store.json
tap_recharge/schemas/metafields_subscription.json
tap_recharge/schemas/onetimes.json
tap_recharge/schemas/orders.json
tap_recharge/schemas/plans.json
tap_recharge/schemas/products.json
tap_recharge/schemas/store.json
tap_recharge/schemas/subscriptions.json
tests/test_recharge_all_fields.py
tests/test_recharge_automated_fields.py
tests/test_recharge_bookmark.py
tests/test_recharge_discovery.py
tests/test_recharge_interrupt_sync.py
tests/test_recharge_pagination.py
tests/test_recharge_start_date.py
tests/test_recharge_sync_canary.py